rednote_mcp_plus/__init__.py
rednote_mcp_plus/__main__.py
rednote_mcp_plus/server.py
rednote_mcp_plus/auth/login.py
rednote_mcp_plus/read/dump.py
rednote_mcp_plus/read/dump_user.py
rednote_mcp_plus/read/search.py
rednote_mcp_plus/write/interaction.py
rednote_mcp_plus/write/publish.py
rednote_mcp_plus-0.7.0.dist-info/licenses/LICENSE
rednote_mcp_plus-0.7.0.dist-info/METADATA
rednote_mcp_plus-0.7.0.dist-info/WHEEL
rednote_mcp_plus-0.7.0.dist-info/entry_points.txt
rednote_mcp_plus-0.7.0.dist-info/top_level.txt
rednote_mcp_plus-0.7.0.dist-info/RECORD
