Metadata-Version: 2.4
Name: rednote_mcp_plus
Version: 0.7.0
Summary: Plus version of MCP server for accessing RedNote
Author-email: MrMao007 <mty1209@gmail.com>
Project-URL: Homepage, https://github.com/MrMao007/RedNote-MCP-Plus
Requires-Python: >=3.10
License-File: LICENSE
Requires-Dist: mcp[cli]
Dynamic: license-file
